{
  "indexes": [
    {
      "collectionGroup": "alumniJobs",
      "queryScope": "COLLECTION",
      "fields": [
        { "fieldPath": "companyId", "order": "ASCENDING" },
        { "fieldPath": "status", "order": "ASCENDING" },
        { "fieldPath": "createdAt", "order": "DESCENDING" }
      ]
    },
    {
      "collectionGroup": "alumniJobs",
      "queryScope": "COLLECTION",
      "fields": [
        { "fieldPath": "companyId", "order": "ASCENDING" },
        { "fieldPath": "createdAt", "order": "DESCENDING" }
      ]
    },
    {
      "collectionGroup": "alumniApplications",
      "queryScope": "COLLECTION",
      "fields": [
        { "fieldPath": "jobId", "order": "ASCENDING" },
        { "fieldPath": "createdAt", "order": "DESCENDING" }
      ]
    },
    {
      "collectionGroup": "alumniAnnouncements",
      "queryScope": "COLLECTION",
      "fields": [
        { "fieldPath": "companyId", "order": "ASCENDING" },
        { "fieldPath": "status", "order": "ASCENDING" },
        { "fieldPath": "createdAt", "order": "DESCENDING" }
      ]
    },
    {
      "collectionGroup": "notifications",
      "queryScope": "COLLECTION",
      "fields": [
        { "fieldPath": "userId", "order": "ASCENDING" },
        { "fieldPath": "createdAt", "order": "DESCENDING" }
      ]
    },
    {
      "collectionGroup": "exitInterviewTemplates",
      "queryScope": "COLLECTION",
      "fields": [
        { "fieldPath": "companyId", "order": "ASCENDING" },
        { "fieldPath": "createdAt", "order": "DESCENDING" }
      ]
    },
    {
      "collectionGroup": "exitInterviewResponses",
      "queryScope": "COLLECTION",
      "fields": [
        { "fieldPath": "companyId", "order": "ASCENDING" },
        { "fieldPath": "createdAt", "order": "DESCENDING" }
      ]
    },
    {
      "collectionGroup": "exitInterviewResponses",
      "queryScope": "COLLECTION",
      "fields": [
        { "fieldPath": "companyId", "order": "ASCENDING" },
        { "fieldPath": "submittedAt", "order": "DESCENDING" }
      ]
    },
    {
      "collectionGroup": "alumniProfiles",
      "queryScope": "COLLECTION",
      "fields": [
        { "fieldPath": "companyId", "order": "ASCENDING" },
        { "fieldPath": "createdAt", "order": "DESCENDING" }
      ]
    },
    {
      "collectionGroup": "offboardFlows",
      "queryScope": "COLLECTION",
      "fields": [
        { "fieldPath": "companyId", "order": "ASCENDING" },
        { "fieldPath": "status", "order": "ASCENDING" },
        { "fieldPath": "completedAt", "order": "DESCENDING" }
      ]
    },
    {
      "collectionGroup": "gigRequests",
      "queryScope": "COLLECTION",
      "fields": [
        { "fieldPath": "alumniId", "order": "ASCENDING" },
        { "fieldPath": "companyId", "order": "ASCENDING" },
        { "fieldPath": "createdAt", "order": "DESCENDING" }
      ]
    },
    {
      "collectionGroup": "gigRequests",
      "queryScope": "COLLECTION",
      "fields": [
        { "fieldPath": "companyId", "order": "ASCENDING" },
        { "fieldPath": "createdAt", "order": "DESCENDING" }
      ]
    },
    {
      "collectionGroup": "docRequests",
      "queryScope": "COLLECTION",
      "fields": [
        { "fieldPath": "alumniId", "order": "ASCENDING" },
        { "fieldPath": "companyId", "order": "ASCENDING" },
        { "fieldPath": "createdAt", "order": "DESCENDING" }
      ]
    },
    {
      "collectionGroup": "docRequests",
      "queryScope": "COLLECTION",
      "fields": [
        { "fieldPath": "companyId", "order": "ASCENDING" },
        { "fieldPath": "createdAt", "order": "DESCENDING" }
      ]
    },
    {
      "collectionGroup": "knowledgeThreads",
      "queryScope": "COLLECTION",
      "fields": [
        { "fieldPath": "alumniId", "order": "ASCENDING" },
        { "fieldPath": "companyId", "order": "ASCENDING" },
        { "fieldPath": "lastMessageAt", "order": "DESCENDING" }
      ]
    },
    {
      "collectionGroup": "knowledgeThreads",
      "queryScope": "COLLECTION",
      "fields": [
        { "fieldPath": "companyId", "order": "ASCENDING" },
        { "fieldPath": "lastMessageAt", "order": "DESCENDING" }
      ]
    },
    {
      "collectionGroup": "knowledgeThreads",
      "queryScope": "COLLECTION",
      "fields": [
        { "fieldPath": "flowId", "order": "ASCENDING" },
        { "fieldPath": "companyId", "order": "ASCENDING" },
        { "fieldPath": "lastMessageAt", "order": "DESCENDING" }
      ]
    },
    {
      "collectionGroup": "alumniProfiles",
      "queryScope": "COLLECTION",
      "fields": [
        { "fieldPath": "companyId", "order": "ASCENDING" },
        { "fieldPath": "name", "order": "ASCENDING" }
      ]
    },
    {
      "collectionGroup": "pulseSurveys",
      "queryScope": "COLLECTION",
      "fields": [
        { "fieldPath": "companyId", "order": "ASCENDING" },
        { "fieldPath": "createdAt", "order": "DESCENDING" }
      ]
    },
    {
      "collectionGroup": "pulseSurveys",
      "queryScope": "COLLECTION",
      "fields": [
        { "fieldPath": "companyId", "order": "ASCENDING" },
        { "fieldPath": "isActive", "order": "ASCENDING" }
      ]
    },
    {
      "collectionGroup": "pulseResponses",
      "queryScope": "COLLECTION",
      "fields": [
        { "fieldPath": "companyId", "order": "ASCENDING" },
        { "fieldPath": "sentAt", "order": "DESCENDING" }
      ]
    }
  ],
  "fieldOverrides": []
}
